myfolder/__init__.py
myfolder/operations.py
math_ops_iiitb-1.0.dist-info/METADATA
math_ops_iiitb-1.0.dist-info/WHEEL
math_ops_iiitb-1.0.dist-info/top_level.txt
math_ops_iiitb-1.0.dist-info/RECORD
