Metadata-Version: 2.1
Name: math_ops_iiitb
Version: 1.0
Summary: A Python package for basic mathematical operations
Home-page: https://github.com/Hemanth-Mada/math_operations
Author: hem
Author-email: hemanthmada001@gmail.com
Classifier: Programming Language :: Python :: 3
Classifier: License :: OSI Approved :: MIT License
Classifier: Operating System :: OS Independent
Requires-Python: >=3.6
